PyTheme.py
PyTheme-0.1.1.dist-info/METADATA
PyTheme-0.1.1.dist-info/WHEEL
PyTheme-0.1.1.dist-info/top_level.txt
PyTheme-0.1.1.dist-info/RECORD
